explainable_ai_sdk/__init__.py
explainable_ai_sdk/version.py
explainable_ai_sdk/common/__init__.py
explainable_ai_sdk/common/attribution.py
explainable_ai_sdk/common/constants.py
explainable_ai_sdk/common/explain_metadata.py
explainable_ai_sdk/common/semver.py
explainable_ai_sdk/common/types.py
explainable_ai_sdk/common/utils.py
explainable_ai_sdk/common/validation_utils.py
explainable_ai_sdk/metadata/__init__.py
explainable_ai_sdk/metadata/constants.py
explainable_ai_sdk/metadata/metadata_builder.py
explainable_ai_sdk/metadata/parameters.py
explainable_ai_sdk/metadata/parameters_test.py
explainable_ai_sdk/metadata/utils.py
explainable_ai_sdk/metadata/utils_test.py
explainable_ai_sdk/metadata/tf/__init__.py
explainable_ai_sdk/metadata/tf/v1/__init__.py
explainable_ai_sdk/metadata/tf/v1/estimator_metadata_builder.py
explainable_ai_sdk/metadata/tf/v1/estimator_metadata_builder_test.py
explainable_ai_sdk/metadata/tf/v1/graph_metadata_builder.py
explainable_ai_sdk/metadata/tf/v1/graph_metadata_builder_test.py
explainable_ai_sdk/metadata/tf/v1/keras_metadata_builder.py
explainable_ai_sdk/metadata/tf/v1/keras_metadata_builder_test.py
explainable_ai_sdk/metadata/tf/v1/monkey_patch_utils.py
explainable_ai_sdk/metadata/tf/v1/monkey_patch_utils_test.py
explainable_ai_sdk/metadata/tf/v1/saved_model_metadata_builder.py
explainable_ai_sdk/metadata/tf/v1/saved_model_metadata_builder_test.py
explainable_ai_sdk/metadata/tf/v1/utils.py
explainable_ai_sdk/metadata/tf/v1/utils_test.py
explainable_ai_sdk/metadata/tf/v2/__init__.py
explainable_ai_sdk/metadata/tf/v2/saved_model_metadata_builder.py
explainable_ai_sdk/model/__init__.py
explainable_ai_sdk/model/ai_platform_model.py
explainable_ai_sdk/model/ai_platform_model_test.py
explainable_ai_sdk/model/configs.py
explainable_ai_sdk/model/constants.py
explainable_ai_sdk/model/explanation.py
explainable_ai_sdk/model/explanation_test.py
explainable_ai_sdk/model/http_utils.py
explainable_ai_sdk/model/http_utils_test.py
explainable_ai_sdk-1.3.3.dist-info/LICENSE
explainable_ai_sdk-1.3.3.dist-info/METADATA
explainable_ai_sdk-1.3.3.dist-info/WHEEL
explainable_ai_sdk-1.3.3.dist-info/top_level.txt
explainable_ai_sdk-1.3.3.dist-info/RECORD
