Metadata-Version: 2.1
Name: explainable-ai-sdk
Version: 1.3.3
Summary: Helper library for CAIP explanations.
Home-page: UNKNOWN
Author: Google LLC
Author-email: xai-dev@googlegroups.com
License: UNKNOWN
Platform: UNKNOWN
License-File: LICENSE
Requires-Dist: google.auth (>=1.14.1)
Requires-Dist: ipython
Requires-Dist: matplotlib (>=3.2.2)
Requires-Dist: numpy (>=1.7)
Requires-Dist: requests (>=2.5)
Requires-Dist: tensorflow (>=1.15.0)
